{
    "name": "{{ cookiecutter.package_name|slugify }}",
    "dockerComposeFile": "../docker-compose.yml",
    "service": "dev",
    "workspaceFolder": "/app/",
    "extensions": [
        "bungcip.better-toml",
        "eamodio.gitlens",
        "ms-azuretools.vscode-docker",
        "ms-python.python",
        "ms-python.vscode-pylance",
        "ryanluker.vscode-coverage-gutters",
        "visualstudioexptteam.vscodeintellicode"
    ],
    "settings": {
        "coverage-gutters.coverageFileNames": [
            "reports/coverage.xml"
        ],
        "editor.codeActionsOnSave": {
            "source.organizeImports": true
        },
        "editor.formatOnPaste": false,
        "editor.formatOnSave": true,
        "editor.rulers": [
            100
        ],
        "files.autoSave": "onFocusChange",
        "python.analysis.typeCheckingMode": "off",
        "python.defaultInterpreterPath": "/usr/local/bin/python",
        "python.formatting.provider": "black",
        "python.languageServer": "Pylance",
        "python.linting.flake8Enabled": true,
        "python.linting.mypyEnabled": true,
        "python.linting.pydocstyleEnabled": true,
        "python.linting.pylintEnabled": false,
        "python.terminal.activateEnvironment": false,
        "python.terminal.activateEnvInCurrentTerminal": false,
        "python.testing.nosetestsEnabled": false,
        "python.testing.pytestEnabled": true,
        "python.testing.unittestEnabled": false,
        "terminal.integrated.defaultProfile.linux": "fish",
        "terminal.integrated.inheritEnv": false,
        "terminal.integrated.profiles.linux": {
            "fish": {
                "path": "/usr/bin/fish"
            }
        }
    }
}